odoo9_addon_base_external_dbsource-9.0.1.0.1-py2.7-nspkg.pth
odoo9_addon_base_external_dbsource-9.0.1.0.1.dist-info/top_level.txt
odoo9_addon_base_external_dbsource-9.0.1.0.1.dist-info/WHEEL
odoo9_addon_base_external_dbsource-9.0.1.0.1.dist-info/RECORD
odoo9_addon_base_external_dbsource-9.0.1.0.1.dist-info/metadata.json
odoo9_addon_base_external_dbsource-9.0.1.0.1.dist-info/DESCRIPTION.rst
odoo9_addon_base_external_dbsource-9.0.1.0.1.dist-info/METADATA
odoo9_addon_base_external_dbsource-9.0.1.0.1.dist-info/namespace_packages.txt
odoo_addons/base_external_dbsource/__openerp__.py
odoo_addons/base_external_dbsource/__init__.py
odoo_addons/base_external_dbsource/README.rst
odoo_addons/base_external_dbsource/security/ir.model.access.csv
odoo_addons/base_external_dbsource/models/__init__.py
odoo_addons/base_external_dbsource/models/base_external_dbsource.py
odoo_addons/base_external_dbsource/i18n/ja.po
odoo_addons/base_external_dbsource/i18n/lv.po
odoo_addons/base_external_dbsource/i18n/zh_CN.po
odoo_addons/base_external_dbsource/i18n/nb_NO.po
odoo_addons/base_external_dbsource/i18n/uk.po
odoo_addons/base_external_dbsource/i18n/es_AR.po
odoo_addons/base_external_dbsource/i18n/ko.po
odoo_addons/base_external_dbsource/i18n/ru.po
odoo_addons/base_external_dbsource/i18n/gl_ES.po
odoo_addons/base_external_dbsource/i18n/pt.po
odoo_addons/base_external_dbsource/i18n/fr_CH.po
odoo_addons/base_external_dbsource/i18n/it.po
odoo_addons/base_external_dbsource/i18n/es_CL.po
odoo_addons/base_external_dbsource/i18n/es.po
odoo_addons/base_external_dbsource/i18n/nl_BE.po
odoo_addons/base_external_dbsource/i18n/ar.po
odoo_addons/base_external_dbsource/i18n/lt.po
odoo_addons/base_external_dbsource/i18n/vi_VN.po
odoo_addons/base_external_dbsource/i18n/ro.po
odoo_addons/base_external_dbsource/i18n/tr.po
odoo_addons/base_external_dbsource/i18n/sr.po
odoo_addons/base_external_dbsource/i18n/es_PY.po
odoo_addons/base_external_dbsource/i18n/mk.po
odoo_addons/base_external_dbsource/i18n/hr.po
odoo_addons/base_external_dbsource/i18n/bg.po
odoo_addons/base_external_dbsource/i18n/es_EC.po
odoo_addons/base_external_dbsource/i18n/zh_TW.po
odoo_addons/base_external_dbsource/i18n/hu.po
odoo_addons/base_external_dbsource/i18n/fr_CA.po
odoo_addons/base_external_dbsource/i18n/gl.po
odoo_addons/base_external_dbsource/i18n/lt_LT.po
odoo_addons/base_external_dbsource/i18n/ca.po
odoo_addons/base_external_dbsource/i18n/id.po
